algo_trader/__init__.py
algo_trader/clients/__init__.py
algo_trader/clients/binance/__init__.py
algo_trader/clients/binance/binance_client.py
algo_trader/clients/binance/binance_order.py
algo_trader/clients/bitmex/__init__.py
algo_trader/clients/bitmex/bitmex_client.py
algo_trader/clients/bitmex/bitmex_order.py
algo_trader/settings/__init__.py
algo_trader/settings/api_links.py
algo_trader/startbot.py
algo_trader/strategies/__init__.py
algo_trader/strategies/lotus.py
algo_trader-3.2.5.dist-info/entry_points.txt
algo_trader-3.2.5.dist-info/LICENSE.rst
algo_trader-3.2.5.dist-info/WHEEL
algo_trader-3.2.5.dist-info/METADATA
algo_trader-3.2.5.dist-info/RECORD
