Metadata-Version: 2.1
Name: algo-trader
Version: 3.2.5
Summary: "Trade execution engine to process API data and transmit orders to Bitmex and other brokers."
License: MIT
Author: Niclas Hummel
Author-email: info@algoinvest.online
Maintainer: Niclas Hummel
Maintainer-email: info@algoinvest.online
Requires-Python: >=3.6,<3.10
Classifier: License :: OSI Approved :: MIT License
Classifier: Programming Language :: Python :: 3
Classifier: Programming Language :: Python :: 3.6
Classifier: Programming Language :: Python :: 3.7
Classifier: Programming Language :: Python :: 3.8
Classifier: Programming Language :: Python :: 3.9
Requires-Dist: binance (>=0.3,<0.4)
Requires-Dist: bitmex (>=0.2.2,<0.3.0)
Requires-Dist: bravado (>=11.0.3,<12.0.0)
